{"metadata": {"dbt_schema_version": "https://schemas.getdbt.com/dbt/run-results/v4.json", "dbt_version": "1.4.5", "generated_at": "2023-08-12T19:10:11.133700Z", "invocation_id": "b6714c2d-6e38-42e4-a260-fe3f6e800793", "env": {}}, "results": [{"status": "success", "timing": [{"name": "compile", "started_at": "2023-08-12T19:09:54.699690Z", "completed_at": "2023-08-12T19:09:54.703183Z"}, {"name": "execute", "started_at": "2023-08-12T19:09:54.704358Z", "completed_at": "2023-08-12T19:10:01.354165Z"}], "thread_id": "Thread-1", "execution_time": 6.66522741317749, "adapter_response": {"_message": "CREATE TABLE (174.4k rows, 21.3 MB processed)", "code": "CREATE TABLE", "rows_affected": 174397, "bytes_processed": 22296018, "location": "US", "project_id": "aec-students", "job_id": "35759287-9fb4-4cc1-8c90-aaf1f60f3d94", "slot_ms": 10151}, "message": "CREATE TABLE (174.4k rows, 21.3 MB processed)", "failures": null, "unique_id": "model.coffee_shop.customers"}, {"status": "success", "timing": [{"name": "compile", "started_at": "2023-08-12T19:10:01.361211Z", "completed_at": "2023-08-12T19:10:01.365348Z"}, {"name": "execute", "started_at": "2023-08-12T19:10:01.366443Z", "completed_at": "2023-08-12T19:10:01.963785Z"}], "thread_id": "Thread-4", "execution_time": 0.6047906875610352, "adapter_response": {"_message": "CREATE VIEW (0 processed)", "code": "CREATE VIEW", "bytes_processed": 0, "location": "US", "project_id": "aec-students", "job_id": "e7aab84b-fb8e-4cff-ada4-8b092075497a", "slot_ms": 0}, "message": "CREATE VIEW (0 processed)", "failures": null, "unique_id": "model.coffee_shop.monthly_customers"}, {"status": "success", "timing": [{"name": "compile", "started_at": "2023-08-12T19:09:54.695827Z", "completed_at": "2023-08-12T19:09:54.704012Z"}, {"name": "execute", "started_at": "2023-08-12T19:09:54.725707Z", "completed_at": "2023-08-12T19:10:10.186496Z"}], "thread_id": "Thread-2", "execution_time": 15.494245767593384, "adapter_response": {"_message": "CREATE TABLE (5.8m rows, 606.0 MB processed)", "code": "CREATE TABLE", "rows_affected": 5797791, "bytes_processed": 635425762, "location": "US", "project_id": "aec-students", "job_id": "24b92e31-4fa9-46bf-9801-27f5c5587e6b", "slot_ms": 157267}, "message": "CREATE TABLE (5.8m rows, 606.0 MB processed)", "failures": null, "unique_id": "model.coffee_shop.user_stitching"}, {"status": "error", "timing": [], "thread_id": "Thread-6", "execution_time": 0.9334673881530762, "adapter_response": {}, "message": "Database Error in model sessions (models/sessions.sql)\n  Syntax error: Expected \")\" but got \",\" at [15:3]\n  compiled Code at target/run/coffee_shop/models/sessions.sql", "failures": null, "unique_id": "model.coffee_shop.sessions"}], "elapsed_time": 21.05526089668274, "args": {"write_json": true, "use_colors": true, "printer_width": 80, "version_check": true, "partial_parse": true, "static_parser": true, "profiles_dir": "/home/vscode/.dbt", "send_anonymous_usage_stats": true, "quiet": false, "no_print": false, "cache_selected_only": false, "which": "run", "rpc_method": "run", "indirect_selection": "eager"}}